README.md
setup.py
geodesic/__init__.py
geodesic/__version__.py
geodesic/main.py
timi_geodesic.egg-info/PKG-INFO
timi_geodesic.egg-info/SOURCES.txt
timi_geodesic.egg-info/dependency_links.txt
timi_geodesic.egg-info/top_level.txt